{
  "_id": "5ffcf7591301a026520601bf",
  "repoId": "PARTNER_DEFAULT_NO_CUSTOMER_ng-staging-en-001",
  "id": 12,
  "type": "step",
  "actions": [
    {
      "source": [
        "Context.set('name', Context.get('currentMessage'))\nWorkflow.branch(13) "
      ],
      "_id": "5ffdf81d31c43de6c20fbf23",
      "id": "723fb759-37b7-4f4f-af08-db67035b96d3"
    }
  ],
  "reactions": [
    {
      "source": [
        "Template.compile(\"What's your name my friend?\")"
      ],
      "_id": "5ffdf81d31c43df5110fbf24",
      "id": "2818e089-dc71-4f0f-833c-c252511f7ce7"
    }
  ],
  "triggers": null,
  "__v": 0,
  "name": "ask-name"
}